poker/__init__.py
poker/__main__.py
poker/utils/__init__.py
poker/utils/action.py
poker/utils/card.py
poker/utils/chip.py
poker/utils/constants.py
poker/utils/deck.py
poker/utils/exception.py
poker/utils/game.py
poker/utils/message.py
poker/utils/player.py
play_poker-0.1.2.dist-info/LICENSE
play_poker-0.1.2.dist-info/WHEEL
play_poker-0.1.2.dist-info/METADATA
play_poker-0.1.2.dist-info/RECORD
