Metadata-Version: 2.1
Name: play-poker
Version: 0.1.2
Summary: Command Line Single-player game of Texas Hold'Em poker
Keywords: poker,games,cards,texas holdem
Author: Ben Griffith
Requires-Python: >=3.9
Classifier: License :: OSI Approved :: MIT License
Requires-Dist: emoji
Requires-Dist: Faker
Requires-Dist: rich
Requires-Dist: pytest ; extra == "test"
Project-URL: Source, https://github.com/bengriffith/poker
Provides-Extra: test
